{"data":[{"id":"1","G1":"﻿\"\"\"UCHTEPA PAXTA TOZALASH\"\" aksiyadorlik jamiyati\"","G2":"1\r"},{"id":"2","G1":"Арнасой тумани Тиббиёт бирлашмаси","G2":"1\r"},{"id":"3","G1":"Арнасой туман Газ унитар корхонаси","G2":"1\r"},{"id":"4","G1":"Арнасой туман Ободонлаштириш бошкармаси","G2":"1\r"},{"id":"5","G1":"Бахмал ТТБ","G2":"1\r"},{"id":"6","G1":"Бахмал Педагогика коллежи","G2":"1\r"},{"id":"7","G1":"Бахмал Қишлоқ хўжалик КХК","G2":"1\r"},{"id":"8","G1":"Бахмал ижтимоий-иқтисодиёт КХК","G2":"1\r"},{"id":"9","G1":"Бахмал Компютер техналогиялари КХК","G2":"\r"},{"id":"10","G1":"Бахмал Узунбулоқ маиший хизмат КХК","G2":"1\r"},{"id":"11","G1":"Бахмал Ижтимоий-иқтисодиёт ва педагогика КХК","G2":"1\r"},{"id":"12","G1":"Бахмал тумани 2-сонли ўрта мактаб","G2":"1\r"},{"id":"13","G1":"Бахмал тумани 4-сонли ўрта мактаб","G2":"1\r"},{"id":"14","G1":"Бахмал тумани 10-сонли ўрта мактаб","G2":"1\r"},{"id":"15","G1":"Ғаллаорол туман Тиббиет бирлашмаси","G2":"2\r"},{"id":"16","G1":"Ғаллаорол туман Ободонлаштириш бошкармаси","G2":"1\r"},{"id":"17","G1":"\"\"\"МАРЖОH СУВИ\"\" санаторийси\"","G2":"2\r"},{"id":"18","G1":"Ғаллаорол туман Ёш болалар сил касаллигига карашли санаторияси","G2":"1\r"},{"id":"19","G1":"ЖПИ кошидаги 2-сонли Академик лицейи","G2":"1\r"},{"id":"20","G1":" Дўстлик тумани Пахта тоз.корхонаси ","G2":"1\r"},{"id":"21","G1":"Дўстлик Дон ОАЖ","G2":"2\r"},{"id":"22","G1":" Дўстлик тумани Тиббиёт бирлашмаси","G2":"1\r"},{"id":"23","G1":"Fresh Stayul  MCHJ","G2":"1\r"},{"id":"24","G1":"Ш.Рашидов тумани тиббиёт бирлашмаси","G2":"1\r"},{"id":"25","G1":"Ш.Рашидов тумани мелиоратив экспедицияси","G2":"1\r"},{"id":"26","G1":"Ш.Рашидов тумани Саноат касб-ҳунар коллежи","G2":"1\r"},{"id":"27","G1":"\"Ш.Рашидов тумани \"\"Жиззах санаторияси\"\"\"","G2":"1\r"},{"id":"28","G1":"Ш.Рашидов тумани 16-сон умумий ўрта таълим мактаби","G2":"1\r"},{"id":"29","G1":"Ш.Рашидов тумани 29-сон умумий ўрта таълим мактаби","G2":"1\r"},{"id":"30","G1":"Ш.Рашидов тумани 32-сон умумий ўрта таълим мактаби","G2":"1\r"},{"id":"31","G1":"Ш.Рашидов тумани Силга қарши кураш диспансери","G2":"1\r"},{"id":"32","G1":"\"\"\"Агробанк\"\" АТБ Ш.Рашидов тумани филиали\"","G2":"1\r"},{"id":"33","G1":"\"\"\"MILKFOODS\"\"  МЧЖ\"","G2":"1\r"},{"id":"34","G1":"\"Зарбдор тумани \"\"БУСТОН\"\"  саноат  касб хунар коллежи\"","G2":"1\r"},{"id":"35","G1":"Зарбдор тумани тиббиет бирлашмаси","G2":"1\r"},{"id":"36","G1":"Zarbdor xizmat ko`rsatish kolleji","G2":"1\r"},{"id":"37","G1":"\"Зарбдор тумани хокимлиги \"\"ОБОДОHЛАШТИРИШ БОШКАРМАСИ\"\"\"","G2":"1\r"},{"id":"38","G1":"\"\"\"Зафаробод пахта тозалаш \"\" ОАЖ\"","G2":"1\r"},{"id":"39","G1":"Зафаробод тумани тиббиёт бирлашмаси","G2":"1\r"},{"id":"40","G1":"\"Зафаробод тумани \"\"Ободонлаштириш бошқармаси\"\"\"","G2":"1\r"},{"id":"41","G1":"Зафаробод тумани Маиший хизмат касб-ҳунар коллежи","G2":"1\r"},{"id":"42","G1":"Зафаробод тумани 2-сонли умумий ўрта таълим мактаби","G2":"1\r"},{"id":"43","G1":"Зафаробод тумани 16-сонли умумий ўрта таълим мактаби","G2":"1\r"},{"id":"44","G1":"Зомин тумани М.Мирзиёев номли тиббиёт бирлашмаси","G2":"2\r"},{"id":"45","G1":"\"\"\"ZOMIN SANATORIYASI\"\" mas`uliyati cheklangan jamiyati\"","G2":"1\r"},{"id":"46","G1":"\"\"\"МУРУВВАТ\"\" ногиронлар учун аёллар интернат уйи\"","G2":"1\r"},{"id":"47","G1":"Зомин тиббиёт коллежи","G2":"1\r"},{"id":"48","G1":"Зомин тумани 50-son umumiy o'rta ta'lim maktabi","G2":"1\r"},{"id":"49","G1":"Зомин тумани 60-son umumiy o'rta ta'lim maktabi","G2":"1\r"},{"id":"50","G1":"Мирзачул тумани тиббиет бирлашмаси","G2":"1\r"},{"id":"51","G1":"\"\"\"MIRZACHULDAVSUVMAXSUS PUDRAT\"\" davlat unitar korxonasi\"","G2":"1\r"},{"id":"52","G1":"Mirzacho'l tumani 18-sonli umumiy o'rta ta'lim maktabi","G2":"1\r"},{"id":"53","G1":"Mirzacho'l tumani 16-sonli umumiy o'rta ta'lim maktabi","G2":"1\r"},{"id":"54","G1":"Mirzacho'l tumani 14-sonli umumiy o'rta ta'lim maktabi","G2":"1\r"},{"id":"55","G1":"Mirzacho'l tumani 12-sonli umumiy o'rta ta'lim maktabi","G2":"1\r"},{"id":"56","G1":"Mirzacho'l tumani 11-sonli umumiy o'rta ta'lim maktabi","G2":"1\r"},{"id":"57","G1":"Жанубий мирзачул магистрал канали","G2":"1\r"},{"id":"58","G1":"\" МЧЖ шаклдаги \"\"PAXTAKOR SIFAT YOG'\"\" Ўзбекистон Буюк Британия қўш. корхонаси\"","G2":"1\r"},{"id":"59","G1":"Пахтакор тумани 3-мактаб","G2":"1\r"},{"id":"60","G1":"Пахтакор тумани 12-мактаб","G2":"1\r"},{"id":"61","G1":"Пахтакор тумани 17-мактаб","G2":"1\r"},{"id":"62","G1":"Пахтакор тумани Иктисодиёт касб-хунар коллежи","G2":"1\r"},{"id":"63","G1":"Пахтакор тумани Булбулча Асад МТМ","G2":"1\r"},{"id":"64","G1":"\"\"\"JIZZAX BAXORI\"\" mas`uliyati cheklangan jamiyati\"","G2":"1\r"},{"id":"65","G1":"\"Пахтакор тумани \"\"А.ТЕМУР\"\" кишлок врачлик пункти\"","G2":"1\r"},{"id":"66","G1":"Фориш тумани Ободонлаштириш бошқармаси","G2":"1\r"},{"id":"67","G1":"Фориш тумани  Туман тиббиёт бирлашмаси","G2":"2\r"},{"id":"68","G1":"Фориш тумани Автойўл","G2":"1\r"},{"id":"69","G1":"Фориш тумани Қишлоқ хўжалиги касб-ҳунар коллежи","G2":"1\r"},{"id":"70","G1":"Фориш тумани Маиший хизмат кўрсатиш касб-ҳунар коллежи","G2":"1\r"},{"id":"71","G1":"Фориш ижтимоий иқтисодий коллеж","G2":"1\r"},{"id":"72","G1":" Янгиобод тумани Туман тиббиёт бирлашмаси","G2":"1\r"},{"id":"73","G1":"  Янгиобод тумани Агроиқтисодиёт касб-ҳунар коллежи","G2":"1\r"},{"id":"74","G1":" Янгиобод тумани 1-сон умумий ўрта таълим мактаби","G2":"1\r"},{"id":"75","G1":" Янгиобод тумани 12-сон умумий ўрта таълим мактаби","G2":"1\r"},{"id":"76","G1":"\"\"\"Республика шошилинч тез тиббий ёрдам илмий маркази\"\" Жиззах вилояти филиали\"","G2":"1\r"},{"id":"77","G1":"Абдулла Қодирий номидаги Жиззах давлат педагогика институти","G2":"1\r"},{"id":"78","G1":"\"\"\"Республика ихтисослаштирилган акушерлик ва гинекология илмий-текшириш маркази\"\" Жиззах филиали\"","G2":"1\r"},{"id":"79","G1":"Жиззах шаҳар Сувокова корхонаси","G2":"1\r"},{"id":"80","G1":"11-сон умумий ўрта таълим мактаби","G2":"1\r"},{"id":"81","G1":"Жиззах вилояти Онкология касалликлари диспансери","G2":"1\r"},{"id":"82","G1":"2-сон умумий ўрта таълим мактаби","G2":"1\r"},{"id":"83","G1":"10-сон умумий ўрта таълим мактаби","G2":"1\r"},{"id":"84","G1":" АТ Алока банк Жиззах филиали  ","G2":"1\r"},{"id":"85","G1":"7-сон умумий ўрта таълим мактаби","G2":"1\r"},{"id":"86","G1":"Жиззах вилояти Стомотология поликлиникаси","G2":"1\r"},{"id":"87","G1":"\"\"\"Hаврўз\"\" номли 39-сонли мактабгача таълим муассасаси\"","G2":"1\r"},{"id":"88","G1":"\"\"\"Дўстлик\"\" номли 10-сон мактабгача таълим муассассаси\"","G2":"1\r"},{"id":"89","G1":"Жиззах вилоят Ахборот кутубхона маркази","G2":"1\r"},{"id":"90","G1":"Жиззах вилояти болалар сил касалликлари шифохонаси","G2":"1\r"},{"id":"91","G1":"Жиззах вилояти Орттирилган иммунитет танқислик синдроми маркази","G2":"1\r"},{"id":"92","G1":"Жиззах вилояти Қон қуйиш маркази","G2":"1\r"},{"id":"93","G1":"\"Жиззах вилояти \"\"Она ва бола скрининг маркази\"\"\"","G2":"1\r"},{"id":"94","G1":"Жиззах вилояти ногиронлар реабилитация маркази","G2":"1\r"},{"id":"95","G1":"\"\"\"REMSTROYSERVIS\"\" МЧЖ\"","G2":"1\r"},{"id":"96","G1":"","G2":"\r"},{"id":"97","G1":"","G2":"\r"},{"id":"98","G1":"","G2":"\r"},{"id":"99","G1":"","G2":"\r"},{"id":"100","G1":"","G2":"\r"},{"id":"101","G1":"","G2":"\r"},{"id":"102","G1":"","G2":"\r"},{"id":"103","G1":"","G2":"\r"},{"id":"104","G1":"","G2":"\r"},{"id":"105","G1":"","G2":"\r"},{"id":"106","G1":"","G2":"\r"},{"id":"107","G1":"","G2":"\r"},{"id":"108","G1":"","G2":"\r"},{"id":"109","G1":"","G2":"\r"},{"id":"110","G1":"","G2":"\r"},{"id":"111","G1":"","G2":"\r"},{"id":"112","G1":"","G2":"\r"},{"id":"113","G1":"","G2":"\r"},{"id":"114","G1":"","G2":"\r"},{"id":"115","G1":"","G2":"\r"},{"id":"116","G1":"","G2":"\r"},{"id":"117","G1":"","G2":"\r"},{"id":"118","G1":"","G2":"\r"},{"id":"119","G1":"","G2":"\r"},{"id":"120","G1":"","G2":"\r"},{"id":"121","G1":"","G2":"\r"},{"id":"122","G1":"","G2":"\r"},{"id":"123","G1":"","G2":"\r"},{"id":"124","G1":"","G2":"\r"},{"id":"125","G1":"","G2":"\r"}]}
